{
  "mainAssemblyName": "Sabatex.RadzenBlazor.Demo",
  "resources": {
    "hash": "sha256-iRtjDo607Ho4UfV6Rq/p+yaUUI8jd/jQSLkkZtsZqNo=",
    "fingerprinting": {
      "Markdig.b3xwtrjo89.wasm": "Markdig.wasm",
      "Microsoft.AspNetCore.Authorization.2w73kwsssx.wasm": "Microsoft.AspNetCore.Authorization.wasm",
      "Microsoft.AspNetCore.Components.5quia5yi6x.wasm": "Microsoft.AspNetCore.Components.wasm",
      "Microsoft.AspNetCore.Components.Authorization.7cleppani7.wasm": "Microsoft.AspNetCore.Components.Authorization.wasm",
      "Microsoft.AspNetCore.Components.Forms.10rq3ezq5u.wasm": "Microsoft.AspNetCore.Components.Forms.wasm",
      "Microsoft.AspNetCore.Components.Web.0twowc2nte.wasm": "Microsoft.AspNetCore.Components.Web.wasm",
      "Microsoft.AspNetCore.Components.WebAssembly.d5dcth9zwy.wasm": "Microsoft.AspNetCore.Components.WebAssembly.wasm",
      "Microsoft.AspNetCore.Metadata.gmpisozv5d.wasm": "Microsoft.AspNetCore.Metadata.wasm",
      "Microsoft.Extensions.Configuration.cyz6aj3end.wasm": "Microsoft.Extensions.Configuration.wasm",
      "Microsoft.Extensions.Configuration.Abstractions.85u9862gz3.wasm": "Microsoft.Extensions.Configuration.Abstractions.wasm",
      "Microsoft.Extensions.Configuration.Json.0cm6d8ej68.wasm": "Microsoft.Extensions.Configuration.Json.wasm",
      "Microsoft.Extensions.DependencyInjection.uum8fsrbn4.wasm": "Microsoft.Extensions.DependencyInjection.wasm",
      "Microsoft.Extensions.DependencyInjection.Abstractions.51et7j9yx7.wasm": "Microsoft.Extensions.DependencyInjection.Abstractions.wasm",
      "Microsoft.Extensions.Localization.4d6r2tb18w.wasm": "Microsoft.Extensions.Localization.wasm",
      "Microsoft.Extensions.Localization.Abstractions.omh1hdyz67.wasm": "Microsoft.Extensions.Localization.Abstractions.wasm",
      "Microsoft.Extensions.Logging.p9svcbtg1a.wasm": "Microsoft.Extensions.Logging.wasm",
      "Microsoft.Extensions.Logging.Abstractions.9nlsprpemd.wasm": "Microsoft.Extensions.Logging.Abstractions.wasm",
      "Microsoft.Extensions.Options.684cvt6ofy.wasm": "Microsoft.Extensions.Options.wasm",
      "Microsoft.Extensions.Primitives.5pxr7nzxwe.wasm": "Microsoft.Extensions.Primitives.wasm",
      "Microsoft.JSInterop.thg64f7yod.wasm": "Microsoft.JSInterop.wasm",
      "Microsoft.JSInterop.WebAssembly.imfqvv3x5h.wasm": "Microsoft.JSInterop.WebAssembly.wasm",
      "Radzen.Blazor.b38uiux5qw.wasm": "Radzen.Blazor.wasm",
      "Sabatex.Core.pibqlzjns5.wasm": "Sabatex.Core.wasm",
      "Sabatex.RadzenBlazor.4cz5b5x4py.wasm": "Sabatex.RadzenBlazor.wasm",
      "Microsoft.CSharp.ppzrxrw6a0.wasm": "Microsoft.CSharp.wasm",
      "System.Collections.Concurrent.5dg27qw3mn.wasm": "System.Collections.Concurrent.wasm",
      "System.Collections.Immutable.9wjem99jup.wasm": "System.Collections.Immutable.wasm",
      "System.Collections.NonGeneric.5fqaa2ju7o.wasm": "System.Collections.NonGeneric.wasm",
      "System.Collections.Specialized.j4cbilqd6x.wasm": "System.Collections.Specialized.wasm",
      "System.Collections.gg3rr0tt2e.wasm": "System.Collections.wasm",
      "System.ComponentModel.Annotations.jj302cyugb.wasm": "System.ComponentModel.Annotations.wasm",
      "System.ComponentModel.Primitives.ruhptkfg11.wasm": "System.ComponentModel.Primitives.wasm",
      "System.ComponentModel.TypeConverter.9y8o9sxxc1.wasm": "System.ComponentModel.TypeConverter.wasm",
      "System.ComponentModel.5y3o4qq5pj.wasm": "System.ComponentModel.wasm",
      "System.Console.cem5zkkqfp.wasm": "System.Console.wasm",
      "System.Core.mi5id249j0.wasm": "System.Core.wasm",
      "System.Data.Common.umeq0mk01d.wasm": "System.Data.Common.wasm",
      "System.Diagnostics.DiagnosticSource.tge9i76ciu.wasm": "System.Diagnostics.DiagnosticSource.wasm",
      "System.Drawing.Primitives.ipk39d478j.wasm": "System.Drawing.Primitives.wasm",
      "System.Drawing.ewphiunpcg.wasm": "System.Drawing.wasm",
      "System.IO.Pipelines.kapd30rafw.wasm": "System.IO.Pipelines.wasm",
      "System.Linq.Expressions.i6ipon6ekq.wasm": "System.Linq.Expressions.wasm",
      "System.Linq.Queryable.468fbptu2s.wasm": "System.Linq.Queryable.wasm",
      "System.Linq.e5etqgbedh.wasm": "System.Linq.wasm",
      "System.Memory.7yrz34v2p6.wasm": "System.Memory.wasm",
      "System.Net.Http.Json.jlunhvlrcf.wasm": "System.Net.Http.Json.wasm",
      "System.Net.Http.bmbze38ra4.wasm": "System.Net.Http.wasm",
      "System.Net.Primitives.0h7y3g6nqf.wasm": "System.Net.Primitives.wasm",
      "System.ObjectModel.e7c0pzin5h.wasm": "System.ObjectModel.wasm",
      "System.Private.Uri.3thymb5wer.wasm": "System.Private.Uri.wasm",
      "System.Private.Xml.Linq.ojoky2x6ju.wasm": "System.Private.Xml.Linq.wasm",
      "System.Private.Xml.i2hk6gn8z7.wasm": "System.Private.Xml.wasm",
      "System.Reflection.Emit.ILGeneration.xydwfugpt6.wasm": "System.Reflection.Emit.ILGeneration.wasm",
      "System.Reflection.Emit.moyk3dnjd3.wasm": "System.Reflection.Emit.wasm",
      "System.Reflection.Primitives.s2j1s28uhr.wasm": "System.Reflection.Primitives.wasm",
      "System.Runtime.InteropServices.JavaScript.f7txb1es0b.wasm": "System.Runtime.InteropServices.JavaScript.wasm",
      "System.Runtime.InteropServices.t4gipi9sfm.wasm": "System.Runtime.InteropServices.wasm",
      "System.Runtime.Serialization.Primitives.b9zxhpbsq0.wasm": "System.Runtime.Serialization.Primitives.wasm",
      "System.Runtime.ih608ud8l3.wasm": "System.Runtime.wasm",
      "System.Security.Claims.16kquojzwc.wasm": "System.Security.Claims.wasm",
      "System.Text.Encodings.Web.ujbee8yy9l.wasm": "System.Text.Encodings.Web.wasm",
      "System.Text.Json.0gd4x3lk18.wasm": "System.Text.Json.wasm",
      "System.Text.RegularExpressions.3trtodlfqy.wasm": "System.Text.RegularExpressions.wasm",
      "System.Threading.ff2vmnk05t.wasm": "System.Threading.wasm",
      "System.Web.HttpUtility.wsed2e1pbx.wasm": "System.Web.HttpUtility.wasm",
      "System.Xml.Linq.qsgzs1hc1j.wasm": "System.Xml.Linq.wasm",
      "System.Xml.XDocument.bh6q24w1sa.wasm": "System.Xml.XDocument.wasm",
      "System.m0fu6d0eya.wasm": "System.wasm",
      "System.Private.CoreLib.7thgaei5vg.wasm": "System.Private.CoreLib.wasm",
      "Sabatex.RadzenBlazor.Demo.fsm13fl06a.wasm": "Sabatex.RadzenBlazor.Demo.wasm",
      "Sabatex.Core.resources.1bxy918b0o.wasm": "Sabatex.Core.resources.wasm",
      "Sabatex.RadzenBlazor.resources.oahzp4muaw.wasm": "Sabatex.RadzenBlazor.resources.wasm",
      "dotnet.js": "dotnet.js",
      "dotnet.native.9ih887ebfz.js": "dotnet.native.js",
      "dotnet.native.21mns4qp4i.wasm": "dotnet.native.wasm",
      "dotnet.runtime.st3wwc8rqy.js": "dotnet.runtime.js",
      "icudt_CJK.tjcz0u77k5.dat": "icudt_CJK.dat",
      "icudt_EFIGS.tptq2av103.dat": "icudt_EFIGS.dat",
      "icudt_no_CJK.lfu7j35m59.dat": "icudt_no_CJK.dat"
    },
    "jsModuleNative": {
      "dotnet.native.9ih887ebfz.js": "sha256-oS7IRiQoVt9ThQ7Y2UM3XoeY0JqPD02cg9IvRdufn2w="
    },
    "jsModuleRuntime": {
      "dotnet.runtime.st3wwc8rqy.js": "sha256-oBRKHAqZUsvCRnCzkQfB7zc45cpKLNq2NKyrG10IKx8="
    },
    "wasmNative": {
      "dotnet.native.21mns4qp4i.wasm": "sha256-RtuwNrUOdAJ5A4aS4ZmceO4ySriaYqTdC7X++6yd9lM="
    },
    "icu": {
      "icudt_CJK.tjcz0u77k5.dat": "sha256-SZLtQnRc0JkwqHab0VUVP7T3uBPSeYzxzDnpxPpUnHk=",
      "icudt_EFIGS.tptq2av103.dat": "sha256-8fItetYY8kQ0ww6oxwTLiT3oXlBwHKumbeP2pRF4yTc=",
      "icudt_no_CJK.lfu7j35m59.dat": "sha256-L7sV7NEYP37/Qr2FPCePo5cJqRgTXRwGHuwF5Q+0Nfs="
    },
    "coreAssembly": {
      "System.Runtime.InteropServices.JavaScript.f7txb1es0b.wasm": "sha256-5X6FWiZE4NSx4s9iNjfVim2lWQpcbVIsorx1vB6lyno=",
      "System.Private.CoreLib.7thgaei5vg.wasm": "sha256-1Z95b+boxzL1bWbeeZE9x3syWtM/hD57shC5d6W9XJE="
    },
    "assembly": {
      "Markdig.b3xwtrjo89.wasm": "sha256-hyj+5aHc/Z0gokcosJ8D9/8TtYpRRyZJHI9CDtuo4kw=",
      "Microsoft.AspNetCore.Authorization.2w73kwsssx.wasm": "sha256-TuHj5ssFCLndEvqfyOU/Fhc1wlXUccTZH7vp0vLJOJQ=",
      "Microsoft.AspNetCore.Components.5quia5yi6x.wasm": "sha256-DYqteYyOgNgp2GTyjPOMuTfYSKm/t8XnT/ikk2qMlbk=",
      "Microsoft.AspNetCore.Components.Authorization.7cleppani7.wasm": "sha256-eX9epkQSB1HUvfecxf66uG109w5lNKBqWzaN70Rf39c=",
      "Microsoft.AspNetCore.Components.Forms.10rq3ezq5u.wasm": "sha256-MZZTpP2g9lt3OcfLxg1njwUrYdFpdiftU6DWllfokjI=",
      "Microsoft.AspNetCore.Components.Web.0twowc2nte.wasm": "sha256-7JP/9EI7Uia5WylVUEOHZaj6BKRI6DpjP7djY+tgfwA=",
      "Microsoft.AspNetCore.Components.WebAssembly.d5dcth9zwy.wasm": "sha256-kT4nJ4FzCv8y+W6On7sCtiUy2xhdGUe1sw3FgbJmRPg=",
      "Microsoft.AspNetCore.Metadata.gmpisozv5d.wasm": "sha256-OD7cjWUJ209opH9IGzfiwAAFM0G3SeYv5KeSwjLl9aI=",
      "Microsoft.Extensions.Configuration.cyz6aj3end.wasm": "sha256-fN4AyqImDQ+h3H7tFeF4ZSkjIHJ7qWgbKL217x6P53s=",
      "Microsoft.Extensions.Configuration.Abstractions.85u9862gz3.wasm": "sha256-3ADlF4CLU1Q+dQbj0MnPVnEJPiA4q4Jv5xxmiGEvBks=",
      "Microsoft.Extensions.Configuration.Json.0cm6d8ej68.wasm": "sha256-kKMubKJ3c2lATxpoAuoDqMjzQ+a0M6Ym35pK74cMK2o=",
      "Microsoft.Extensions.DependencyInjection.uum8fsrbn4.wasm": "sha256-Sgs1bgmGaF2mv6rWcaihc+x48ZQQAidfzYwZvYX5WJk=",
      "Microsoft.Extensions.DependencyInjection.Abstractions.51et7j9yx7.wasm": "sha256-t3CE47vYQ6zRC/gv2pVAqA2Z8M53ftN8+KeCz3xos5M=",
      "Microsoft.Extensions.Localization.4d6r2tb18w.wasm": "sha256-COGIH7l+iLC9osGHV6joSp9WaHN5iNXMcQourYY4XjY=",
      "Microsoft.Extensions.Localization.Abstractions.omh1hdyz67.wasm": "sha256-gAssamQIbTevquBNPj9X6SDMBpEomnx67DiY6WwG0Jg=",
      "Microsoft.Extensions.Logging.p9svcbtg1a.wasm": "sha256-I/euMiwOKn2U2Y1vqcUjYWEG/7zWmvDiTlHAoPLRHQ0=",
      "Microsoft.Extensions.Logging.Abstractions.9nlsprpemd.wasm": "sha256-a46hXU/pDe/suWrF3e8v5rxhPnX/mO1WHeJG/vOT460=",
      "Microsoft.Extensions.Options.684cvt6ofy.wasm": "sha256-ZhMP66Xdwsxg3woDGMbE/PrgYbF1Ok/Fju/43KlNEtI=",
      "Microsoft.Extensions.Primitives.5pxr7nzxwe.wasm": "sha256-WXYpl64HUqc9+prJOz6dOEVvB8PFJhTdfqUMB3ZGRGA=",
      "Microsoft.JSInterop.thg64f7yod.wasm": "sha256-/1ZLYN7kGbiaf5A1mRrzPPLlkM3ztDqm+RYpw/p9ceY=",
      "Microsoft.JSInterop.WebAssembly.imfqvv3x5h.wasm": "sha256-mpyjzA6YBuV9Qx5BUC8YbXP9YjZlM+k7YTVawzXJFgk=",
      "Radzen.Blazor.b38uiux5qw.wasm": "sha256-d16U1yI8YpNiSO10W4XzZOv37r/A8dJbvt9/04LPsU4=",
      "Sabatex.Core.pibqlzjns5.wasm": "sha256-0U3HGJH3R+Y19oJiB9q6NapcyJGSGW/0XBEgAiSp4LA=",
      "Sabatex.RadzenBlazor.4cz5b5x4py.wasm": "sha256-3I7xW1kaywnXhqbVFXFGKYtfFlWPN8vpQH/Tpambg+0=",
      "Microsoft.CSharp.ppzrxrw6a0.wasm": "sha256-c4VNnxCS/7i4eyB1cTZrH0JKAjCUz5jWo8DvxcYOH2o=",
      "System.Collections.Concurrent.5dg27qw3mn.wasm": "sha256-WY7oA0yARcNn8NhdsE1+wysftfVMV/5ChW2ri6eSj28=",
      "System.Collections.Immutable.9wjem99jup.wasm": "sha256-x7kpK7vvIiK8Oy5w0k7nFoq44KqJdbFzAFEVKjQBK6o=",
      "System.Collections.NonGeneric.5fqaa2ju7o.wasm": "sha256-QebNkQryDxN25Q7cvUuwOCtyqNGH+4wwZCepYSOGAFs=",
      "System.Collections.Specialized.j4cbilqd6x.wasm": "sha256-I7h/7ddX61kZM04cR3y32oSterzKgBc9x9lHJZLH7D0=",
      "System.Collections.gg3rr0tt2e.wasm": "sha256-QFXjPRd3tgBT5grro88vnTJk9JMYmfKhfRgnDcmoZAU=",
      "System.ComponentModel.Annotations.jj302cyugb.wasm": "sha256-EVylM3ytQByZ//AbNeIvWvMdttHN5vp+LWvP6PNZTkM=",
      "System.ComponentModel.Primitives.ruhptkfg11.wasm": "sha256-XdzW1zcnBiW+VvNa7kSiXfzJ2IvaX6ueh3A3T7EES10=",
      "System.ComponentModel.TypeConverter.9y8o9sxxc1.wasm": "sha256-USzpYt5sZ3VQNTKikqpGFx0rrFGBDn5U8inlT/4vQg0=",
      "System.ComponentModel.5y3o4qq5pj.wasm": "sha256-/TUgJRG3EZB5Bcfo9BEFJ61DIJLAJRTXeLYB1vnMd1Q=",
      "System.Console.cem5zkkqfp.wasm": "sha256-XGyj6mJKAibaka1K6PF2ZMsU0Tptsee9wMwP4/HBx+E=",
      "System.Core.mi5id249j0.wasm": "sha256-kh4hWB30Fm3u3oP8n59f5LFE0lS6vqtyU8IQzKs5oO8=",
      "System.Data.Common.umeq0mk01d.wasm": "sha256-atswtAASP4K/V/BrJirrNYAvmzDJrE+b/Nzd48w/BSA=",
      "System.Diagnostics.DiagnosticSource.tge9i76ciu.wasm": "sha256-gyDSa5r5b9+T3/LLN701Ns2ydjSZDu9XPBN7yc5DB8I=",
      "System.Drawing.Primitives.ipk39d478j.wasm": "sha256-loiXSFF1+Zo5TBlJtfBil42YyTPVd8LYEkutf9ZnakE=",
      "System.Drawing.ewphiunpcg.wasm": "sha256-oiiMus6vWgrlohxq9qh1XosItYfnyEecLBjVPRvbLHI=",
      "System.IO.Pipelines.kapd30rafw.wasm": "sha256-tCvlwGJAx3TJMot5V3EE7CsL75IH2QH821792tEpUhM=",
      "System.Linq.Expressions.i6ipon6ekq.wasm": "sha256-StyLrlZLUXVjWWtxe2QtDoA21iFrVqzkGh/WnChPFv4=",
      "System.Linq.Queryable.468fbptu2s.wasm": "sha256-HBaxWdFKhpBg2RkUIRc8W4B/nr4Mwb6uHmO0OsqspzI=",
      "System.Linq.e5etqgbedh.wasm": "sha256-HklIWI7wpyuArCDx2UWul0mcZvaqeiA2ywqYR/eWhMQ=",
      "System.Memory.7yrz34v2p6.wasm": "sha256-P1sR18gJFiZR099QPZ+/NJvf/NBv202v7FhVSJSIPlg=",
      "System.Net.Http.Json.jlunhvlrcf.wasm": "sha256-WWgclmnD7k3WhI7aFg88xggBh802G/3Q4g92HKDWuyc=",
      "System.Net.Http.bmbze38ra4.wasm": "sha256-kx9zdIvOj9lYEtIL2NzP7ZoRtPR+DTySXRH83RAJ4nI=",
      "System.Net.Primitives.0h7y3g6nqf.wasm": "sha256-rGIYM/g7mFHB4tUKXxzKAMTdeOGYJ8NmnYQ66r9vFwE=",
      "System.ObjectModel.e7c0pzin5h.wasm": "sha256-ykJ1xusIsrZzLFIdCA1xUAirElXE8djMb4N/UeYz0OQ=",
      "System.Private.Uri.3thymb5wer.wasm": "sha256-WT+RxyUm+UaGGV9O6OgTXGZrcFPNTy0OvP+V8xI1O7A=",
      "System.Private.Xml.Linq.ojoky2x6ju.wasm": "sha256-RPPMxOp8NXB3Mpw4g7uAtBkTpUhh99GWC/1vwBXtn1Q=",
      "System.Private.Xml.i2hk6gn8z7.wasm": "sha256-lvaRjLwwH+3BnmBBtAq/UX8WlWOI5gaSu1eQWHksIJg=",
      "System.Reflection.Emit.ILGeneration.xydwfugpt6.wasm": "sha256-Rwrv2JGR2BXnB0UEeAnykKPE+DWRlxiEPQvnYNGkheo=",
      "System.Reflection.Emit.moyk3dnjd3.wasm": "sha256-llO4bpLg0jQSZzTSkTE8JMMtAFEVqHXVulPeY3CJ6zE=",
      "System.Reflection.Primitives.s2j1s28uhr.wasm": "sha256-1PpEowNT285pH9QLabbBJhUwVk5N8pShAHK7R24yP/c=",
      "System.Runtime.InteropServices.t4gipi9sfm.wasm": "sha256-LfM6BypmGux3PI4QlIFNgVImNiJP2cT2bRxIdmr+NEc=",
      "System.Runtime.Serialization.Primitives.b9zxhpbsq0.wasm": "sha256-v5VUTg84n8lTiYdSZXSYXy9m0WC2k99Ij2F6RCjblTc=",
      "System.Runtime.ih608ud8l3.wasm": "sha256-Ks/8eZXNJf6K0+Q8sgQpXGfr5fvIIvvKGZSaV0xiWn0=",
      "System.Security.Claims.16kquojzwc.wasm": "sha256-mRZ0N7ugfut+CkSG7lEUFEn2nS9GNoziPpSv8Z2Zoec=",
      "System.Text.Encodings.Web.ujbee8yy9l.wasm": "sha256-BkAo1wUO1j2o4gAgHdIcf5krMaKLY2JTATftC8u/rHw=",
      "System.Text.Json.0gd4x3lk18.wasm": "sha256-EBqbyPy792UoJiV1GvpsPqCKutKzzJHl55/aiIc6QvI=",
      "System.Text.RegularExpressions.3trtodlfqy.wasm": "sha256-B64adZoDNqoYcIavZF7NZcfAiYHz5dYtHbpFibRUl68=",
      "System.Threading.ff2vmnk05t.wasm": "sha256-C/AUG9JZAC5iks6D3bDfW96IeOqOyh+0V7svrdir2HA=",
      "System.Web.HttpUtility.wsed2e1pbx.wasm": "sha256-0OnLnH9EvbzQVEDezQQPsV1xdkAOloFM0xMuE2gnyDc=",
      "System.Xml.Linq.qsgzs1hc1j.wasm": "sha256-yo+J3RWIIHIiwAhqsR9JizNkH/+hd3auB44RBmvvLoI=",
      "System.Xml.XDocument.bh6q24w1sa.wasm": "sha256-sUpLFuNZQPCWGlQhhlmQjvC+8foGtglJhLTZ0lvunDY=",
      "System.m0fu6d0eya.wasm": "sha256-hkGLo/MuT/FJ0Xf4XUL0D2VA4dZV532GHNB1JicxLko=",
      "Sabatex.RadzenBlazor.Demo.fsm13fl06a.wasm": "sha256-YQd4FXuzNPfoZ7hImNEbQAplz+w5WM3/gW/na982H2U="
    },
    "satelliteResources": {
      "uk": {
        "Sabatex.Core.resources.1bxy918b0o.wasm": "sha256-HWo/GizJUcIcWIXvGJd48c73IjNjPAq0DTAarRHIRB8=",
        "Sabatex.RadzenBlazor.resources.oahzp4muaw.wasm": "sha256-UGu1dG1mVdEQMWmwIepdijsQK0LH45nuGucQKYuauaI="
      }
    }
  },
  "cacheBootResources": true,
  "debugLevel": 0,
  "linkerEnabled": true,
  "globalizationMode": "sharded",
  "extensions": {
    "blazor": {}
  }
}